protoc_docs/__init__.py
protoc_docs/code.py
protoc_docs/parser.py
protoc_docs/bin/__init__.py
protoc_docs/bin/py_desc_converter.py
protoc_docs/bin/py_desc_converter_pandoc.py
protoc_docs/bin/py_docstring.py
protoc_docs/bin/py_docstring_pandoc.py
protoc_docs_plugin-0.8.0.dist-info/LICENSE
protoc_docs_plugin-0.8.0.dist-info/METADATA
protoc_docs_plugin-0.8.0.dist-info/WHEEL
protoc_docs_plugin-0.8.0.dist-info/entry_points.txt
protoc_docs_plugin-0.8.0.dist-info/top_level.txt
protoc_docs_plugin-0.8.0.dist-info/RECORD
