Metadata-Version: 2.1
Name: protoc-docs-plugin
Version: 0.8.0
Summary: Plugin for reading and writing documentation from protobuf files into existing generated protoc output.
Home-page: https://github.com/googleapis/protoc-docs-plugin
Author: Luke Sneeringer
Author-email: lukesneeringer@google.com
License: Apache-2.0
Platform: UNKNOWN
Classifier: Development Status :: 4 - Beta
Classifier: Environment :: Console
Classifier: Intended Audience :: Developers
Classifier: License :: OSI Approved :: Apache Software License
Classifier: Programming Language :: Python
Classifier: Programming Language :: Python :: 2.7
Classifier: Programming Language :: Python :: 3.4
Classifier: Programming Language :: Python :: 3.5
Classifier: Programming Language :: Python :: 3.6
Requires-Dist: protobuf (>=3.3.0)
Requires-Dist: pypandoc (>=1.4)
